openproject_google_calendar/__init__.py
openproject_google_calendar/main.py
openproject_google_calendar/google_calendar/__init__.py
openproject_google_calendar/google_calendar/calendar.py
openproject_google_calendar/openproject/__init__.py
openproject_google_calendar/openproject/project.py
openproject_google_calendar/openproject/work_package.py
openproject_google_calendar-0.2.dist-info/DESCRIPTION.rst
openproject_google_calendar-0.2.dist-info/METADATA
openproject_google_calendar-0.2.dist-info/RECORD
openproject_google_calendar-0.2.dist-info/WHEEL
openproject_google_calendar-0.2.dist-info/entry_points.txt
openproject_google_calendar-0.2.dist-info/metadata.json
openproject_google_calendar-0.2.dist-info/top_level.txt
openproject_google_calendar-0.2.dist-info/zip-safe
